<?xml version="1.0" encoding="utf-8"?>
<SoundBanksInfo Platform="Windows" BasePlatform="Windows" SchemaVersion="12" SoundbankVersion="135">
	<RootPaths>
		<ProjectRoot>C:\Users\Cole Krueger\Documents\GitHub\TheLastShip\TheLastShip\TheLastShip_WwiseProject\</ProjectRoot>
		<SourceFilesRoot>C:\Users\Cole Krueger\Documents\GitHub\TheLastShip\TheLastShip\TheLastShip_WwiseProject\.cache\Windows\</SourceFilesRoot>
		<SoundBanksRoot>C:\Users\Cole Krueger\Documents\GitHub\TheLastShip\TheLastShip\TheLastShip_WwiseProject\GeneratedSoundBanks\Windows\</SoundBanksRoot>
		<ExternalSourcesInputFile></ExternalSourcesInputFile>
		<ExternalSourcesOutputRoot>C:\Users\Cole Krueger\Documents\GitHub\TheLastShip\TheLastShip\TheLastShip_WwiseProject\GeneratedSoundBanks\Windows</ExternalSourcesOutputRoot>
	</RootPaths>
	<DialogueEvents/>
	<StreamedFiles/>
	<MediaFilesNotInAnyBank/>
	<SoundBanks>
		<SoundBank Id="1355168291" Language="SFX">
			<ObjectPath>Init</ObjectPath>
			<ShortName>Init</ShortName>
			<Path>Init.bnk</Path>
		</SoundBank>
		<SoundBank Id="2880737896" Language="SFX">
			<ObjectPath>\SoundBanks\Default Work Unit\MainBank</ObjectPath>
			<ShortName>MainBank</ShortName>
			<Path>MainBank.bnk</Path>
			<IncludedEvents>
				<Event Id="1670947946" Name="plr_engine" ObjectPath="\Events\Default Work Unit\plr_engine" DurationType="Infinite">
					<IncludedMemoryFiles>
						<File Id="16333983" Language="SFX">
							<ShortName>sx_plr_engine_slower.wav</ShortName>
							<Path>SFX\sx_plr_engine_slower_D79FB2B7.wem</Path>
						</File>
						<File Id="291291475" Language="SFX">
							<ShortName>sx_plr_engine_whine.wav</ShortName>
							<Path>SFX\sx_plr_engine_whine_D79FB2B7.wem</Path>
						</File>
						<File Id="828196131" Language="SFX">
							<ShortName>sx_plr_engine_faster.wav</ShortName>
							<Path>SFX\sx_plr_engine_faster_D79FB2B7.wem</Path>
						</File>
					</IncludedMemoryFiles>
				</Event>
				<Event Id="181840089" Name="plr_engine_stop" ObjectPath="\Events\Default Work Unit\plr_engine_stop" MaxAttenuation="0.000000" DurationType="OneShot" DurationMin="0.000000" DurationMax="0.000000"/>
				<Event Id="614170710" Name="plr_primary_shoot" ObjectPath="\Events\Default Work Unit\plr_primary_shoot" DurationType="OneShot" DurationMin="0.305220" DurationMax="0.309660">
					<IncludedMemoryFiles>
						<File Id="259940942" Language="SFX">
							<ShortName>sx_plr_main_cannon_5.wav</ShortName>
							<Path>SFX\sx_plr_main_cannon_5_10C4C929.wem</Path>
						</File>
						<File Id="270555747" Language="SFX">
							<ShortName>sx_plr_main_cannon_4.wav</ShortName>
							<Path>SFX\sx_plr_main_cannon_4_10C4C929.wem</Path>
						</File>
						<File Id="341271279" Language="SFX">
							<ShortName>sx_plr_main_cannon_3.wav</ShortName>
							<Path>SFX\sx_plr_main_cannon_3_10C4C929.wem</Path>
						</File>
						<File Id="402433319" Language="SFX">
							<ShortName>sx_plr_main_cannon_1.wav</ShortName>
							<Path>SFX\sx_plr_main_cannon_1_10C4C929.wem</Path>
						</File>
						<File Id="868942418" Language="SFX">
							<ShortName>sx_plr_main_cannon_2.wav</ShortName>
							<Path>SFX\sx_plr_main_cannon_2_10C4C929.wem</Path>
						</File>
					</IncludedMemoryFiles>
				</Event>
				<Event Id="2898173329" Name="plr_secondary_charge" ObjectPath="\Events\Default Work Unit\plr_secondary_charge" DurationType="Infinite">
					<IncludedMemoryFiles>
						<File Id="623822031" Language="SFX">
							<ShortName>sx_plr_secondary_charge.wav</ShortName>
							<Path>SFX\sx_plr_secondary_charge_10C4C929.wem</Path>
						</File>
						<File Id="695854333" Language="SFX">
							<ShortName>sx_plr_secondary_loop.wav</ShortName>
							<Path>SFX\sx_plr_secondary_loop_D79FB2B7.wem</Path>
						</File>
					</IncludedMemoryFiles>
				</Event>
				<Event Id="33059316" Name="plr_secondary_charge_stop" ObjectPath="\Events\Default Work Unit\plr_secondary_charge_stop" MaxAttenuation="0.000000" DurationType="OneShot" DurationMin="0.000000" DurationMax="0.000000"/>
				<Event Id="3600127465" Name="plr_shield_damage" ObjectPath="\Events\Default Work Unit\plr_shield_damage" DurationType="OneShot" DurationMin="0.776795" DurationMax="1.038821">
					<IncludedMemoryFiles>
						<File Id="170695096" Language="SFX">
							<ShortName>sx_plr_shield_hit_1.wav</ShortName>
							<Path>SFX\sx_plr_shield_hit_1_10C4C929.wem</Path>
						</File>
						<File Id="330943432" Language="SFX">
							<ShortName>sx_plr_shield_hit_4.wav</ShortName>
							<Path>SFX\sx_plr_shield_hit_4_10C4C929.wem</Path>
						</File>
						<File Id="657373504" Language="SFX">
							<ShortName>sx_plr_shield_hit_2.wav</ShortName>
							<Path>SFX\sx_plr_shield_hit_2_10C4C929.wem</Path>
						</File>
						<File Id="1008552407" Language="SFX">
							<ShortName>sx_plr_shield_hit_3.wav</ShortName>
							<Path>SFX\sx_plr_shield_hit_3_10C4C929.wem</Path>
						</File>
					</IncludedMemoryFiles>
				</Event>
			</IncludedEvents>
			<GameParameters>
				<GameParameter Id="1062779386" Name="Player_Speed" ObjectPath="\Game Parameters\Default Work Unit\Player_Speed"/>
			</GameParameters>
		</SoundBank>
	</SoundBanks>
</SoundBanksInfo>
